researchme/libgen/__init__.py
researchme/libgen/_scrapper_sessions.py
ResearchMe-0.1.2.dist-info/LICENSE
ResearchMe-0.1.2.dist-info/METADATA
ResearchMe-0.1.2.dist-info/WHEEL
ResearchMe-0.1.2.dist-info/top_level.txt
ResearchMe-0.1.2.dist-info/RECORD
