Metadata-Version: 2.1
Name: ResearchMe
Version: 0.1.2
Summary: A Python library for programmatic access to Library Genesis
Author: Tabinda Touqeer
License: MIT
Project-URL: Homepage, https://github.com/tabinda-touqeer/ResearchMe
Project-URL: Repository, https://github.com/tabinda-touqeer/ResearchMe
Classifier: Programming Language :: Python :: 3
Classifier: License :: OSI Approved :: MIT License
Classifier: Operating System :: OS Independent
Requires-Python: >=3.7
License-File: LICENSE
Requires-Dist: requests>=2.25.0
Requires-Dist: beautifulsoup4>=4.9.0
Requires-Dist: urllib3>=1.26.0
